{
	"folders": {},
	"connections": {
		"postgres-jdbc-18925626644-636cd4f1e8996e02": {
			"provider": "postgresql",
			"driver": "postgres-jdbc",
			"name": "postgres",
			"save-password": true,
			"show-system-objects": true,
			"configuration": {
				"host": "localhost",
				"port": "5432",
				"database": "postgres",
				"url": "jdbc:postgresql://localhost:5432/postgres",
				"configurationType": "MANUAL",
				"home": "postgresql-x64-15",
				"type": "dev",
				"auth-model": "native"
			}
		}
	},
	"connection-types": {
		"dev": {
			"name": "Development",
			"color": "255,255,255",
			"description": "Regular development database",
			"auto-commit": true,
			"confirm-execute": false,
			"confirm-data-change": false,
			"smart-commit": false,
			"smart-commit-recover": true,
			"auto-close-transactions": true,
			"close-transactions-period": 1800
		}
	}
}